rotins/__init__.py
rotins/core.py
rotins/py.typed
rotins-1.0.0.dist-info/licenses/LICENSE
rotins-1.0.0.dist-info/METADATA
rotins-1.0.0.dist-info/WHEEL
rotins-1.0.0.dist-info/top_level.txt
rotins-1.0.0.dist-info/zip-safe
rotins-1.0.0.dist-info/RECORD
