Metadata-Version: 2.4
Name: rotins
Version: 1.0.0
Summary: A Python package for rotational and instrumental broadening of stellar spectra
Home-page: https://github.com/k-sriram/rotins
Author: Sriram Krishna
Author-email: Sriram Krishna <email@example.com>
License: MIT
Project-URL: Homepage, https://github.com/k-sriram/rotins
Project-URL: Documentation, https://github.com/k-sriram/rotins#readme
Project-URL: Issues, https://github.com/k-sriram/rotins/issues
Project-URL: Source, https://github.com/k-sriram/rotins
Keywords: astronomy,spectroscopy,stellar spectra,broadening,astrophysics
Classifier: Development Status :: 5 - Production/Stable
Classifier: Intended Audience :: Science/Research
Classifier: License :: OSI Approved :: MIT License
Classifier: Programming Language :: Python :: 3
Classifier: Programming Language :: Python :: 3.8
Classifier: Programming Language :: Python :: 3.9
Classifier: Programming Language :: Python :: 3.10
Classifier: Programming Language :: Python :: 3.11
Classifier: Topic :: Scientific/Engineering :: Astronomy
Classifier: Topic :: Scientific/Engineering :: Physics
Requires-Python: >=3.8
License-File: LICENSE
Requires-Dist: numpy>=1.17.0
Requires-Dist: scipy>=1.5.0
Dynamic: license-file
